OCChaos/Chaos.py
OCChaos/Logger.py
OCChaos/OCChaosConfig.py
OCChaos/OCChaosImgMd5Change.py
OCChaos/OCChaosPrefixRe.py
OCChaos/OCChaosUselessClassfile.py
OCChaos/OCChaosUselessCode.py
OCChaos/__init__.py
occhaos-1.0.6.dist-info/DESCRIPTION.rst
occhaos-1.0.6.dist-info/METADATA
occhaos-1.0.6.dist-info/RECORD
occhaos-1.0.6.dist-info/WHEEL
occhaos-1.0.6.dist-info/entry_points.txt
occhaos-1.0.6.dist-info/metadata.json
occhaos-1.0.6.dist-info/top_level.txt
occhaos-1.0.6.dist-info/zip-safe
